odoo/addons/sale_product_classification/README.rst
odoo/addons/sale_product_classification/__init__.py
odoo/addons/sale_product_classification/__manifest__.py
odoo/addons/sale_product_classification/data/ir_cron.xml
odoo/addons/sale_product_classification/i18n/es.po
odoo/addons/sale_product_classification/i18n/sale_product_classification.pot
odoo/addons/sale_product_classification/models/__init__.py
odoo/addons/sale_product_classification/models/product_product.py
odoo/addons/sale_product_classification/models/product_template.py
odoo/addons/sale_product_classification/models/res_company.py
odoo/addons/sale_product_classification/models/res_config_settings.py
odoo/addons/sale_product_classification/readme/CONFIGURE.rst
odoo/addons/sale_product_classification/readme/CONTRIBUTORS.rst
odoo/addons/sale_product_classification/readme/DESCRIPTION.rst
odoo/addons/sale_product_classification/readme/ROADMAP.rst
odoo/addons/sale_product_classification/readme/USAGE.rst
odoo/addons/sale_product_classification/static/description/icon.png
odoo/addons/sale_product_classification/static/description/index.html
odoo/addons/sale_product_classification/tests/__init__.py
odoo/addons/sale_product_classification/tests/test_sale_product_classification.py
odoo/addons/sale_product_classification/tests/test_sale_product_classification_common.py
odoo/addons/sale_product_classification/views/product_template_views.xml
odoo/addons/sale_product_classification/views/res_config_settings_views.xml
odoo12_addon_sale_product_classification-12.0.1.0.0.99.dev4.dist-info/METADATA
odoo12_addon_sale_product_classification-12.0.1.0.0.99.dev4.dist-info/WHEEL
odoo12_addon_sale_product_classification-12.0.1.0.0.99.dev4.dist-info/top_level.txt
odoo12_addon_sale_product_classification-12.0.1.0.0.99.dev4.dist-info/RECORD
